my_own_package/__init__.py
bogdan_pack1-0.1.0.dist-info/METADATA
bogdan_pack1-0.1.0.dist-info/WHEEL
bogdan_pack1-0.1.0.dist-info/top_level.txt
bogdan_pack1-0.1.0.dist-info/RECORD
