Metadata-Version: 2.1
Name: bogdan-pack1
Version: 0.1.0
Summary: primul package facut
Author: bogdan
Author-email: bucur.bogdan1996@yahoo.com
License: UNKNOWN
Platform: UNKNOWN
